ppp/__init__.py
ppp/main.py
stannismod_ppp/__init__.py
stannismod_ppp/main.py
stannismod_ppp-0.1.dist-info/LICENSE.txt
stannismod_ppp-0.1.dist-info/METADATA
stannismod_ppp-0.1.dist-info/WHEEL
stannismod_ppp-0.1.dist-info/top_level.txt
stannismod_ppp-0.1.dist-info/RECORD
